{
    "bookSourceComment": "",
    "bookSourceGroup": "",
    "bookSourceName": "笔趣阁②",
    "bookSourceType": 0,
    "bookSourceUrl": "https://m.quge7.com",
    "customOrder": 368,
    "enabled": true,
    "enabledCookieJar": false,
    "enabledExplore": true,
    "exploreUrl": "[{\"title\":\"玄幻\",\"url\":\"/xuanhuan/?page={{page}}\",\"style\":{\"layout_flexBasisPercent\":0.2,\"layout_flexGrow\":1}},\n{\"title\":\"武侠\",\"url\":\"/wuxia/?page={{page}}\",\"style\":{\"layout_flexBasisPercent\":0.2,\"layout_flexGrow\":1}},\n{\"title\":\"都市\",\"url\":\"/dushi/?page={{page}}\",\"style\":{\"layout_flexBasisPercent\":0.2,\"layout_flexGrow\":1}},\n{\"title\":\"历史\",\"url\":\"/lishi/?page={{page}}\",\"style\":{\"layout_flexBasisPercent\":0.2,\"layout_flexGrow\":1}},\n{\"title\":\"网游\",\"url\":\"/wangyou/?page={{page}}\",\"style\":{\"layout_flexBasisPercent\":0.2,\"layout_flexGrow\":1}},\n{\"title\":\"科幻\",\"url\":\"/kehuan/?page={{page}}\",\"style\":{\"layout_flexBasisPercent\":0.2,\"layout_flexGrow\":1}},\n{\"title\":\"女生\",\"url\":\"/mm/?page={{page}}\",\"style\":{\"layout_flexBasisPercent\":0.2,\"layout_flexGrow\":1}},\n{\"title\":\"全本\",\"url\":\"/finish/?page={{page}}\",\"style\":{\"layout_flexBasisPercent\":0.2,\"layout_flexGrow\":1}}]",
    "lastUpdateTime": 1643456103727,
    "respondTime": 8708,
    "ruleBookInfo": {
        "author": "[property=\"og:novel:author\"]@content",
        "coverUrl": "[property=\"og:image\"]@content",
        "intro": "[property=\"og:description\"]@content##(^|[。！？]+[”」）】]?)##$1<br>",
        "kind": "[property=\"og:novel:category\"]@content&&[property=\"og:novel:status\"]@content&&[property=\"og:novel:update_time\"]@content##\\s.*",
        "lastChapter": "[property=\"og:novel:latest_chapter_name\"]@content",
        "name": "[property=\"og:novel:book_name\"]@content",
        "tocUrl": ".book_more a@href",
        "wordCount": "##字数.([^<]+)<##$1###"
    },
    "ruleContent": {
        "content": "#chaptercontent@textNodes",
        "nextContentUrl": "#pb_next@href"
    },
    "ruleExplore": {
        "author": "",
        "bookList": "",
        "bookUrl": "",
        "coverUrl": "",
        "intro": "",
        "name": ""
    },
    "ruleSearch": {
        "author": "span@text",
        "bookList": ".item",
        "bookUrl": "a.1@href",
        "checkKeyWord": "",
        "coverUrl": "img@src",
        "intro": "dd@text",
        "kind": "",
        "lastChapter": "",
        "name": "a.1@text"
    },
    "ruleToc": {
        "chapterList": ".book_last dd a",
        "chapterName": "text##.*页面底部",
        "chapterUrl": "href"
    },
    "searchUrl": "/s?q={{key}}",
    "weight": 0
}