{
    "bookSourceComment": "",
    "bookSourceGroup": "",
    "bookSourceName": "新笔趣阁",
    "bookSourceType": 0,
    "bookSourceUrl": "https://www.xbiquge.so#",
    "bookUrlPattern": "",
    "concurrentRate": "",
    "customOrder": 26,
    "enabled": true,
    "enabledCookieJar": false,
    "enabledExplore": false,
    "exploreUrl": "",
    "header": "",
    "lastUpdateTime": 1646055690272,
    "loginCheckJs": "",
    "loginUi": "",
    "loginUrl": "",
    "respondTime": 8039,
    "ruleBookInfo": {
        "author": "id.info@tag.p.0@tag.a@text",
        "coverUrl": "id.fmimg@img@src",
        "init": "class.box_con",
        "intro": "id.intro@text",
        "lastChapter": "id.info@tag.p.3@tag.a@text&&id.info@tag.p.2@text##更新时间.|..\\:.*",
        "name": "id.info@tag.h1@text"
    },
    "ruleContent": {
        "content": "id.content@html##一秒记住.*无弹窗免费阅读！|笔趣阁.*最新章节！|笔趣阁.*！"
    },
    "ruleExplore": {},
    "ruleSearch": {
        "author": "class.s4@text",
        "bookList": "class.novelslistss@tag.li",
        "bookUrl": "class.s2@tag.a@href",
        "coverUrl": "class.s2@tag.a@href<js>\nvar id = result.match(/(\\d+)\\/?$/)[1];\nvar iid = parseInt(id/1000);\n'https://www.xbiquge.so/files/article/image/'+iid+'/'+id+'/'+id+'s.jpg';\n</js>",
        "kind": "class.s1@text##\\,&&\nclass.s7@text",
        "lastChapter": "class.s3@tag.a@text&&class.s5@text",
        "name": "class.s2@tag.a@text"
    },
    "ruleToc": {
        "chapterList": "id.list@tag.dd",
        "chapterName": "tag.a@text",
        "chapterUrl": "tag.a@href"
    },
    "searchUrl": "https://www.xbiquge.so/modules/article/search.php?searchkey={{key}}&page={{page}},{\n  \"charset\": \"gbk\"\n}",
    "weight": 0
}