{
    "bookSourceComment": "",
    "bookSourceGroup": "正版,漫画",
    "bookSourceName": "酷爱漫画",
    "bookSourceType": 2,
    "bookSourceUrl": "https://www.kuimh.com",
    "customOrder": 485,
    "enabled": true,
    "enabledCookieJar": false,
    "enabledExplore": true,
    "exploreUrl": "[{\"title\":\"国产\",\"url\":\"/booklist?tag=%E5%85%A8%E9%83%A8&area=1&end=-1&page={{page}}\",\"style\":{\"layout_flexBasisPercent\":1,\"layout_flexGrow\":1}},\n{\"title\":\"恋爱\",\"url\":\"/booklist?tag=恋爱&area=1&end=-1&page={{page}}\",\"style\":{\"layout_flexBasisPercent\":0.25,\"layout_flexGrow\":1}},\n{\"title\":\"古风\",\"url\":\"/booklist?tag=古风&area=1&end=-1&page={{page}}\",\"style\":{\"layout_flexBasisPercent\":0.25,\"layout_flexGrow\":1}},\n{\"title\":\"校园\",\"url\":\"/booklist?tag=校园&area=1&end=-1&page={{page}}\",\"style\":{\"layout_flexBasisPercent\":0.25,\"layout_flexGrow\":1}},\n{\"title\":\"奇幻\",\"url\":\"/booklist?tag=奇幻&area=1&end=-1&page={{page}}\",\"style\":{\"layout_flexBasisPercent\":0.25,\"layout_flexGrow\":1}},\n{\"title\":\"女主\",\"url\":\"/booklist?tag=大女主&area=1&end=-1&page={{page}}\",\"style\":{\"layout_flexBasisPercent\":0.25,\"layout_flexGrow\":1}},\n{\"title\":\"治愈\",\"url\":\"/booklist?tag=治愈&area=1&end=-1&page={{page}}\",\"style\":{\"layout_flexBasisPercent\":0.25,\"layout_flexGrow\":1}},\n{\"title\":\"穿越\",\"url\":\"/booklist?tag=穿越&area=1&end=-1&page={{page}}\",\"style\":{\"layout_flexBasisPercent\":0.25,\"layout_flexGrow\":1}},\n{\"title\":\"励志\",\"url\":\"/booklist?tag=励志&area=1&end=-1&page={{page}}\",\"style\":{\"layout_flexBasisPercent\":0.25,\"layout_flexGrow\":1}},\n{\"title\":\"爆笑\",\"url\":\"/booklist?tag=爆笑&area=1&end=-1&page={{page}}\",\"style\":{\"layout_flexBasisPercent\":0.25,\"layout_flexGrow\":1}},\n{\"title\":\"萌系\",\"url\":\"/booklist?tag=萌系&area=1&end=-1&page={{page}}\",\"style\":{\"layout_flexBasisPercent\":0.25,\"layout_flexGrow\":1}},\n{\"title\":\"玄幻\",\"url\":\"/booklist?tag=玄幻&area=1&end=-1&page={{page}}\",\"style\":{\"layout_flexBasisPercent\":0.25,\"layout_flexGrow\":1}},\n{\"title\":\"日常\",\"url\":\"/booklist?tag=日常&area=1&end=-1&page={{page}}\",\"style\":{\"layout_flexBasisPercent\":0.25,\"layout_flexGrow\":1}},\n{\"title\":\"都市\",\"url\":\"/booklist?tag=都市&area=1&end=-1&page={{page}}\",\"style\":{\"layout_flexBasisPercent\":0.25,\"layout_flexGrow\":1}},\n{\"title\":\"彩虹\",\"url\":\"/booklist?tag=彩虹&area=1&end=-1&page={{page}}\",\"style\":{\"layout_flexBasisPercent\":0.25,\"layout_flexGrow\":1}},\n{\"title\":\"灵异\",\"url\":\"/booklist?tag=灵异&area=1&end=-1&page={{page}}\",\"style\":{\"layout_flexBasisPercent\":0.25,\"layout_flexGrow\":1}},\n{\"title\":\"悬疑\",\"url\":\"/booklist?tag=悬疑&area=1&end=-1&page={{page}}\",\"style\":{\"layout_flexBasisPercent\":0.29}},\n{\"title\":\"少年\",\"url\":\"/booklist?tag=少年&area=1&end=-1&page={{page}}\",\"style\":{\"layout_flexBasisPercent\":0.29}},\n{\"title\":\"日本\",\"url\":\"/booklist?tag=%E5%85%A8%E9%83%A8&area=2&end=-1&page={{page}}\",\"style\":{\"layout_flexBasisPercent\":1,\"layout_flexGrow\":1}},\n{\"title\":\"恋爱\",\"url\":\"/booklist?tag=恋爱&area=2&end=-1&page={{page}}\",\"style\":{\"layout_flexBasisPercent\":0.25,\"layout_flexGrow\":1}},\n{\"title\":\"古风\",\"url\":\"/booklist?tag=古风&area=2&end=-1&page={{page}}\",\"style\":{\"layout_flexBasisPercent\":0.25,\"layout_flexGrow\":1}},\n{\"title\":\"校园\",\"url\":\"/booklist?tag=校园&area=2&end=-1&page={{page}}\",\"style\":{\"layout_flexBasisPercent\":0.25,\"layout_flexGrow\":1}},\n{\"title\":\"奇幻\",\"url\":\"/booklist?tag=奇幻&area=2&end=-1&page={{page}}\",\"style\":{\"layout_flexBasisPercent\":0.25,\"layout_flexGrow\":1}},\n{\"title\":\"女主\",\"url\":\"/booklist?tag=大女主&area=2&end=-1&page={{page}}\",\"style\":{\"layout_flexBasisPercent\":0.25,\"layout_flexGrow\":1}},\n{\"title\":\"治愈\",\"url\":\"/booklist?tag=治愈&area=2&end=-1&page={{page}}\",\"style\":{\"layout_flexBasisPercent\":0.25,\"layout_flexGrow\":1}},\n{\"title\":\"穿越\",\"url\":\"/booklist?tag=穿越&area=2&end=-1&page={{page}}\",\"style\":{\"layout_flexBasisPercent\":0.25,\"layout_flexGrow\":1}},\n{\"title\":\"励志\",\"url\":\"/booklist?tag=励志&area=2&end=-1&page={{page}}\",\"style\":{\"layout_flexBasisPercent\":0.25,\"layout_flexGrow\":1}},\n{\"title\":\"爆笑\",\"url\":\"/booklist?tag=爆笑&area=2&end=-1&page={{page}}\",\"style\":{\"layout_flexBasisPercent\":0.25,\"layout_flexGrow\":1}},\n{\"title\":\"萌系\",\"url\":\"/booklist?tag=萌系&area=2&end=-1&page={{page}}\",\"style\":{\"layout_flexBasisPercent\":0.25,\"layout_flexGrow\":1}},\n{\"title\":\"玄幻\",\"url\":\"/booklist?tag=玄幻&area=2&end=-1&page={{page}}\",\"style\":{\"layout_flexBasisPercent\":0.25,\"layout_flexGrow\":1}},\n{\"title\":\"日常\",\"url\":\"/booklist?tag=日常&area=2&end=-1&page={{page}}\",\"style\":{\"layout_flexBasisPercent\":0.25,\"layout_flexGrow\":1}},\n{\"title\":\"都市\",\"url\":\"/booklist?tag=都市&area=2&end=-1&page={{page}}\",\"style\":{\"layout_flexBasisPercent\":0.25,\"layout_flexGrow\":1}},\n{\"title\":\"彩虹\",\"url\":\"/booklist?tag=彩虹&area=2&end=-1&page={{page}}\",\"style\":{\"layout_flexBasisPercent\":0.25,\"layout_flexGrow\":1}},\n{\"title\":\"灵异\",\"url\":\"/booklist?tag=灵异&area=2&end=-1&page={{page}}\",\"style\":{\"layout_flexBasisPercent\":0.25,\"layout_flexGrow\":1}},\n{\"title\":\"悬疑\",\"url\":\"/booklist?tag=悬疑&area=2&end=-1&page={{page}}\",\"style\":{\"layout_flexBasisPercent\":0.29}},\n{\"title\":\"少年\",\"url\":\"/booklist?tag=少年&area=2&end=-1&page={{page}}\",\"style\":{\"layout_flexBasisPercent\":0.29}},\n{\"title\":\"韩国\",\"url\":\"/booklist?tag=%E5%85%A8%E9%83%A8&area=3&end=-1&page={{page}}\",\"style\":{\"layout_flexBasisPercent\":1,\"layout_flexGrow\":1}},\n{\"title\":\"恋爱\",\"url\":\"/booklist?tag=恋爱&area=3&end=-1&page={{page}}\",\"style\":{\"layout_flexBasisPercent\":0.25,\"layout_flexGrow\":1}},\n{\"title\":\"古风\",\"url\":\"/booklist?tag=古风&area=3&end=-1&page={{page}}\",\"style\":{\"layout_flexBasisPercent\":0.25,\"layout_flexGrow\":1}},\n{\"title\":\"校园\",\"url\":\"/booklist?tag=校园&area=3&end=-1&page={{page}}\",\"style\":{\"layout_flexBasisPercent\":0.25,\"layout_flexGrow\":1}},\n{\"title\":\"奇幻\",\"url\":\"/booklist?tag=奇幻&area=3&end=-1&page={{page}}\",\"style\":{\"layout_flexBasisPercent\":0.25,\"layout_flexGrow\":1}},\n{\"title\":\"女主\",\"url\":\"/booklist?tag=大女主&area=3&end=-1&page={{page}}\",\"style\":{\"layout_flexBasisPercent\":0.25,\"layout_flexGrow\":1}},\n{\"title\":\"治愈\",\"url\":\"/booklist?tag=治愈&area=3&end=-1&page={{page}}\",\"style\":{\"layout_flexBasisPercent\":0.25,\"layout_flexGrow\":1}},\n{\"title\":\"穿越\",\"url\":\"/booklist?tag=穿越&area=3&end=-1&page={{page}}\",\"style\":{\"layout_flexBasisPercent\":0.25,\"layout_flexGrow\":1}},\n{\"title\":\"励志\",\"url\":\"/booklist?tag=励志&area=3&end=-1&page={{page}}\",\"style\":{\"layout_flexBasisPercent\":0.25,\"layout_flexGrow\":1}},\n{\"title\":\"爆笑\",\"url\":\"/booklist?tag=爆笑&area=3&end=-1&page={{page}}\",\"style\":{\"layout_flexBasisPercent\":0.25,\"layout_flexGrow\":1}},\n{\"title\":\"萌系\",\"url\":\"/booklist?tag=萌系&area=3&end=-1&page={{page}}\",\"style\":{\"layout_flexBasisPercent\":0.25,\"layout_flexGrow\":1}},\n{\"title\":\"玄幻\",\"url\":\"/booklist?tag=玄幻&area=3&end=-1&page={{page}}\",\"style\":{\"layout_flexBasisPercent\":0.25,\"layout_flexGrow\":1}},\n{\"title\":\"日常\",\"url\":\"/booklist?tag=日常&area=3&end=-1&page={{page}}\",\"style\":{\"layout_flexBasisPercent\":0.25,\"layout_flexGrow\":1}},\n{\"title\":\"都市\",\"url\":\"/booklist?tag=都市&area=3&end=-1&page={{page}}\",\"style\":{\"layout_flexBasisPercent\":0.25,\"layout_flexGrow\":1}},\n{\"title\":\"彩虹\",\"url\":\"/booklist?tag=彩虹&area=3&end=-1&page={{page}}\",\"style\":{\"layout_flexBasisPercent\":0.25,\"layout_flexGrow\":1}},\n{\"title\":\"灵异\",\"url\":\"/booklist?tag=灵异&area=3&end=-1&page={{page}}\",\"style\":{\"layout_flexBasisPercent\":0.25,\"layout_flexGrow\":1}},\n{\"title\":\"悬疑\",\"url\":\"/booklist?tag=悬疑&area=3&end=-1&page={{page}}\",\"style\":{\"layout_flexBasisPercent\":0.29}},\n{\"title\":\"少年\",\"url\":\"/booklist?tag=少年&area=3&end=-1&page={{page}}\",\"style\":{\"layout_flexBasisPercent\":0.29}},\n{\"title\":\"欧美\",\"url\":\"/booklist?tag=%E5%85%A8%E9%83%A8&area=5&end=-1&page={{page}}\",\"style\":{\"layout_flexBasisPercent\":1,\"layout_flexGrow\":1}},\n{\"title\":\"恋爱\",\"url\":\"/booklist?tag=恋爱&area=5&end=-1&page={{page}}\",\"style\":{\"layout_flexBasisPercent\":0.25,\"layout_flexGrow\":1}},\n{\"title\":\"古风\",\"url\":\"/booklist?tag=古风&area=5&end=-1&page={{page}}\",\"style\":{\"layout_flexBasisPercent\":0.25,\"layout_flexGrow\":1}},\n{\"title\":\"校园\",\"url\":\"/booklist?tag=校园&area=5&end=-1&page={{page}}\",\"style\":{\"layout_flexBasisPercent\":0.25,\"layout_flexGrow\":1}},\n{\"title\":\"奇幻\",\"url\":\"/booklist?tag=奇幻&area=5&end=-1&page={{page}}\",\"style\":{\"layout_flexBasisPercent\":0.25,\"layout_flexGrow\":1}},\n{\"title\":\"女主\",\"url\":\"/booklist?tag=大女主&area=5&end=-1&page={{page}}\",\"style\":{\"layout_flexBasisPercent\":0.25,\"layout_flexGrow\":1}},\n{\"title\":\"治愈\",\"url\":\"/booklist?tag=治愈&area=5&end=-1&page={{page}}\",\"style\":{\"layout_flexBasisPercent\":0.25,\"layout_flexGrow\":1}},\n{\"title\":\"穿越\",\"url\":\"/booklist?tag=穿越&area=5&end=-1&page={{page}}\",\"style\":{\"layout_flexBasisPercent\":0.25,\"layout_flexGrow\":1}},\n{\"title\":\"励志\",\"url\":\"/booklist?tag=励志&area=5&end=-1&page={{page}}\",\"style\":{\"layout_flexBasisPercent\":0.25,\"layout_flexGrow\":1}},\n{\"title\":\"爆笑\",\"url\":\"/booklist?tag=爆笑&area=5&end=-1&page={{page}}\",\"style\":{\"layout_flexBasisPercent\":0.25,\"layout_flexGrow\":1}},\n{\"title\":\"萌系\",\"url\":\"/booklist?tag=萌系&area=5&end=-1&page={{page}}\",\"style\":{\"layout_flexBasisPercent\":0.25,\"layout_flexGrow\":1}},\n{\"title\":\"玄幻\",\"url\":\"/booklist?tag=玄幻&area=5&end=-1&page={{page}}\",\"style\":{\"layout_flexBasisPercent\":0.25,\"layout_flexGrow\":1}},\n{\"title\":\"日常\",\"url\":\"/booklist?tag=日常&area=5&end=-1&page={{page}}\",\"style\":{\"layout_flexBasisPercent\":0.25,\"layout_flexGrow\":1}},\n{\"title\":\"都市\",\"url\":\"/booklist?tag=都市&area=5&end=-1&page={{page}}\",\"style\":{\"layout_flexBasisPercent\":0.25,\"layout_flexGrow\":1}},\n{\"title\":\"彩虹\",\"url\":\"/booklist?tag=彩虹&area=5&end=-1&page={{page}}\",\"style\":{\"layout_flexBasisPercent\":0.25,\"layout_flexGrow\":1}},\n{\"title\":\"灵异\",\"url\":\"/booklist?tag=灵异&area=5&end=-1&page={{page}}\",\"style\":{\"layout_flexBasisPercent\":0.25,\"layout_flexGrow\":1}},\n{\"title\":\"悬疑\",\"url\":\"/booklist?tag=悬疑&area=5&end=-1&page={{page}}\",\"style\":{\"layout_flexBasisPercent\":0.29}},\n{\"title\":\"少年\",\"url\":\"/booklist?tag=少年&area=5&end=-1&page={{page}}\",\"style\":{\"layout_flexBasisPercent\":0.29}},\n{\"title\":\"其他\",\"url\":\"/booklist?tag=%E5%85%A8%E9%83%A8&area=7&end=-1&page={{page}}\",\"style\":{\"layout_flexBasisPercent\":1,\"layout_flexGrow\":1}},\n{\"title\":\"恋爱\",\"url\":\"/booklist?tag=恋爱&area=7&end=-1&page={{page}}\",\"style\":{\"layout_flexBasisPercent\":0.25,\"layout_flexGrow\":1}},\n{\"title\":\"古风\",\"url\":\"/booklist?tag=古风&area=7&end=-1&page={{page}}\",\"style\":{\"layout_flexBasisPercent\":0.25,\"layout_flexGrow\":1}},\n{\"title\":\"校园\",\"url\":\"/booklist?tag=校园&area=7&end=-1&page={{page}}\",\"style\":{\"layout_flexBasisPercent\":0.25,\"layout_flexGrow\":1}},\n{\"title\":\"奇幻\",\"url\":\"/booklist?tag=奇幻&area=7&end=-1&page={{page}}\",\"style\":{\"layout_flexBasisPercent\":0.25,\"layout_flexGrow\":1}},\n{\"title\":\"女主\",\"url\":\"/booklist?tag=大女主&area=7&end=-1&page={{page}}\",\"style\":{\"layout_flexBasisPercent\":0.25,\"layout_flexGrow\":1}},\n{\"title\":\"治愈\",\"url\":\"/booklist?tag=治愈&area=7&end=-1&page={{page}}\",\"style\":{\"layout_flexBasisPercent\":0.25,\"layout_flexGrow\":1}},\n{\"title\":\"穿越\",\"url\":\"/booklist?tag=穿越&area=7&end=-1&page={{page}}\",\"style\":{\"layout_flexBasisPercent\":0.25,\"layout_flexGrow\":1}},\n{\"title\":\"励志\",\"url\":\"/booklist?tag=励志&area=7&end=-1&page={{page}}\",\"style\":{\"layout_flexBasisPercent\":0.25,\"layout_flexGrow\":1}},\n{\"title\":\"爆笑\",\"url\":\"/booklist?tag=爆笑&area=7&end=-1&page={{page}}\",\"style\":{\"layout_flexBasisPercent\":0.25,\"layout_flexGrow\":1}},\n{\"title\":\"萌系\",\"url\":\"/booklist?tag=萌系&area=7&end=-1&page={{page}}\",\"style\":{\"layout_flexBasisPercent\":0.25,\"layout_flexGrow\":1}},\n{\"title\":\"玄幻\",\"url\":\"/booklist?tag=玄幻&area=7&end=-1&page={{page}}\",\"style\":{\"layout_flexBasisPercent\":0.25,\"layout_flexGrow\":1}},\n{\"title\":\"日常\",\"url\":\"/booklist?tag=日常&area=7&end=-1&page={{page}}\",\"style\":{\"layout_flexBasisPercent\":0.25,\"layout_flexGrow\":1}},\n{\"title\":\"都市\",\"url\":\"/booklist?tag=都市&area=7&end=-1&page={{page}}\",\"style\":{\"layout_flexBasisPercent\":0.25,\"layout_flexGrow\":1}},\n{\"title\":\"彩虹\",\"url\":\"/booklist?tag=彩虹&area=7&end=-1&page={{page}}\",\"style\":{\"layout_flexBasisPercent\":0.25,\"layout_flexGrow\":1}},\n{\"title\":\"灵异\",\"url\":\"/booklist?tag=灵异&area=7&end=-1&page={{page}}\",\"style\":{\"layout_flexBasisPercent\":0.25,\"layout_flexGrow\":1}},\n{\"title\":\"悬疑\",\"url\":\"/booklist?tag=悬疑&area=7&end=-1&page={{page}}\",\"style\":{\"layout_flexBasisPercent\":0.29}},\n{\"title\":\"少年\",\"url\":\"/booklist?tag=少年&area=7&end=-1&page={{page}}\",\"style\":{\"layout_flexBasisPercent\":0.29}},\n{\"title\":\"日韩\",\"url\":\"/booklist?tag=%E5%85%A8%E9%83%A8&area=8&end=-1&page={{page}}\",\"style\":{\"layout_flexBasisPercent\":1,\"layout_flexGrow\":1}},\n{\"title\":\"恋爱\",\"url\":\"/booklist?tag=恋爱&area=8&end=-1&page={{page}}\",\"style\":{\"layout_flexBasisPercent\":0.25,\"layout_flexGrow\":1}},\n{\"title\":\"古风\",\"url\":\"/booklist?tag=古风&area=8&end=-1&page={{page}}\",\"style\":{\"layout_flexBasisPercent\":0.25,\"layout_flexGrow\":1}},\n{\"title\":\"校园\",\"url\":\"/booklist?tag=校园&area=8&end=-1&page={{page}}\",\"style\":{\"layout_flexBasisPercent\":0.25,\"layout_flexGrow\":1}},\n{\"title\":\"奇幻\",\"url\":\"/booklist?tag=奇幻&area=8&end=-1&page={{page}}\",\"style\":{\"layout_flexBasisPercent\":0.25,\"layout_flexGrow\":1}},\n{\"title\":\"女主\",\"url\":\"/booklist?tag=大女主&area=8&end=-1&page={{page}}\",\"style\":{\"layout_flexBasisPercent\":0.25,\"layout_flexGrow\":1}},\n{\"title\":\"治愈\",\"url\":\"/booklist?tag=治愈&area=8&end=-1&page={{page}}\",\"style\":{\"layout_flexBasisPercent\":0.25,\"layout_flexGrow\":1}},\n{\"title\":\"穿越\",\"url\":\"/booklist?tag=穿越&area=8&end=-1&page={{page}}\",\"style\":{\"layout_flexBasisPercent\":0.25,\"layout_flexGrow\":1}},\n{\"title\":\"励志\",\"url\":\"/booklist?tag=励志&area=8&end=-1&page={{page}}\",\"style\":{\"layout_flexBasisPercent\":0.25,\"layout_flexGrow\":1}},\n{\"title\":\"爆笑\",\"url\":\"/booklist?tag=爆笑&area=8&end=-1&page={{page}}\",\"style\":{\"layout_flexBasisPercent\":0.25,\"layout_flexGrow\":1}},\n{\"title\":\"萌系\",\"url\":\"/booklist?tag=萌系&area=8&end=-1&page={{page}}\",\"style\":{\"layout_flexBasisPercent\":0.25,\"layout_flexGrow\":1}},\n{\"title\":\"玄幻\",\"url\":\"/booklist?tag=玄幻&area=8&end=-1&page={{page}}\",\"style\":{\"layout_flexBasisPercent\":0.25,\"layout_flexGrow\":1}},\n{\"title\":\"日常\",\"url\":\"/booklist?tag=日常&area=8&end=-1&page={{page}}\",\"style\":{\"layout_flexBasisPercent\":0.25,\"layout_flexGrow\":1}},\n{\"title\":\"都市\",\"url\":\"/booklist?tag=都市&area=8&end=-1&page={{page}}\",\"style\":{\"layout_flexBasisPercent\":0.25,\"layout_flexGrow\":1}},\n{\"title\":\"彩虹\",\"url\":\"/booklist?tag=彩虹&area=8&end=-1&page={{page}}\",\"style\":{\"layout_flexBasisPercent\":0.25,\"layout_flexGrow\":1}},\n{\"title\":\"灵异\",\"url\":\"/booklist?tag=灵异&area=8&end=-1&page={{page}}\",\"style\":{\"layout_flexBasisPercent\":0.25,\"layout_flexGrow\":1}},\n{\"title\":\"悬疑\",\"url\":\"/booklist?tag=悬疑&area=8&end=-1&page={{page}}\",\"style\":{\"layout_flexBasisPercent\":0.29}},\n{\"title\":\"少年\",\"url\":\"/booklist?tag=少年&area=8&end=-1&page={{page}}\",\"style\":{\"layout_flexBasisPercent\":0.29}}]",
    "header": "{\n  \"User-Agent\": \"Mozilla/5.0 (Windows NT 10.0; Win64; x64) AppleWebKit/537.36 (KHTML, like Gecko) Chrome/66.0.3359.203 Safari/537.36\"\n}",
    "lastUpdateTime": 1656252890076,
    "loginUrl": "https://www.kuimh.com/login",
    "respondTime": 1775,
    "ruleBookInfo": {
        "author": "class.subtitle.1@text##作者.",
        "coverUrl": "class.cover.0@img@src",
        "init": "",
        "intro": ".content@p@html",
        "kind": "class.tip.0@a.0@text&&class.tip.0@span.0@text&&class.tip.0@span.3@text##状态.|更新时间.",
        "lastChapter": "#detail-list-select@a.-1@text",
        "name": ".info h1@text",
        "tocUrl": "text.开始阅读@href"
    },
    "ruleContent": {
        "content": ".comicpage@html##\\\"https:\\/\\/static.aiquanjian.com\\/static\\/images\\/grey.gif\\\" data-echo=",
        "imageStyle": "FULL",
        "replaceRegex": "",
        "sourceRegex": ""
    },
    "ruleExplore": {
        "bookList": "",
        "bookUrl": "",
        "coverUrl": "",
        "lastChapter": "",
        "name": ""
    },
    "ruleSearch": {
        "author": "",
        "bookList": ".mh-item",
        "bookUrl": "a.1@href",
        "coverUrl": "p@style@js:result.match(/\\((.*?)\\)/)[1]",
        "kind": "a.2@text",
        "lastChapter": "",
        "name": "a.1@text"
    },
    "ruleToc": {
        "chapterList": ".mCustomScrollBox li",
        "chapterName": "a@text",
        "chapterUrl": "a@href",
        "isVip": "VIP"
    },
    "searchUrl": "/search?keyword={{key}}",
    "weight": 0
}