{
    "bookSourceComment": "",
    "bookSourceGroup": "",
    "bookSourceName": "顶点小说⑤",
    "bookSourceType": 0,
    "bookSourceUrl": "http://www.23us.tw",
    "bookUrlPattern": "https://www.x23us.us/\\d+_\\d+",
    "customOrder": -88902478,
    "enabled": true,
    "enabledCookieJar": false,
    "enabledExplore": true,
    "exploreUrl": "玄幻小说::/xuanhuanxiaoshuo/\n修真小说::/xiuzhenxiaoshuo/\n都市小说::/dushixiaoshuo/\n穿越小说::/chuanyuexiaoshuo/\n网游小说::/wangyouxiaoshuo/\n科幻小说::/kehuanxiaoshuo/\n完本小说::/wanben/\n排行榜单::/paihangbang/",
    "lastUpdateTime": 1657373715686,
    "loginUrl": "",
    "respondTime": 8436,
    "ruleBookInfo": {
        "author": "id.info@tag.p.0@text##作    者：",
        "coverUrl": "id.fmimg@tag.img@src",
        "init": "",
        "intro": "id.intro@text",
        "kind": "id.info@tag.p.2@text##\\更新时间：|\\[|\\]",
        "lastChapter": "id.info@tag.p.3@a@text",
        "name": "id.info@tag.h1.0@text##\\（.*|\\(.*|免费阅读|全文.*阅读|最新章节|笔趣阁|小说"
    },
    "ruleContent": {
        "content": "#content@textNodes",
        "nextContentUrl": ""
    },
    "ruleExplore": {
        "author": "span@text",
        "bookList": ".item",
        "bookUrl": "dt a@href",
        "coverUrl": "img@src",
        "intro": "dd@text",
        "name": "dt a@text"
    },
    "ruleSearch": {
        "author": "tag.td.2@text",
        "bookList": "class.grid@tag.tr!0",
        "bookUrl": "tag.td.0@tag.a@href",
        "coverUrl": "tag.td.0@tag.a@href<js>\nvar id = result.match(/(\\d+)\\/?$/)[1];\nvar iid = parseInt(id/1000);\n'http://www.23us.tw/files/article/image/'+iid+'/'+id+'/'+id+'s.jpg';\n</js>",
        "lastChapter": "tag.td.1@tag.a@text",
        "name": "tag.td.0@tag.a@text##\\（.*|\\(.*|免费阅读|全文.*阅读|最新章节|笔趣阁|小说"
    },
    "ruleToc": {
        "chapterList": "id.list@tag.dd",
        "chapterName": "tag.a@text",
        "chapterUrl": "tag.a@href"
    },
    "searchUrl": "/modules/article/search.php?q={{key}}",
    "weight": 0
}